E3/jkff.v
//Univseridad del Valle de Guatemala
//Gerardo Fuentes
//19389

//Modulo Flipflop tipo D 1 BIT
module DFF1b(input clk, reset, E, D, output reg Q);

  always@(posedge clk, posedge reset, E)
    if (reset)  Q<=1'b0;
    else if (E) Q<=D;

endmodule


//Modulo Flipflop tipo JK 1 BIT
module JKFF1b(input clk2, reset2, J, K, E, output Qn, Qp, nK, nQp, w1, w2);

  not (nK, K);
  not (nQp, Qp);
  and (w1, nK, Qp);
  and (w2, nQp, J);
  or  (Qn, w1, w2);
  DFF1b D1(clk2, reset, E, Qn, Qp);

endmodule

E3/jkff_tb.v
//Univseridad del Valle de Guatemala
//Gerardo Fuentes
//19389

module testbench();

  reg clk, reset, J, K, E;
  wire Qn, Qp, nK, nQp, w1, w2;

  JKFF1b jkf1(clk, reset, J, K, E, Qn, Qp, nK, nQp, w1, w2);


  initial begin
     clk = 0;
     forever #1 clk = ~clk;
  end

  initial begin
    reset = 1;
    #1 reset = 0;
  end

  initial begin
    #1 E = 0; J = 0; K = 0;
    #1 E = 1; J = 0; K = 1;
    #1 E = 1; J = 0; K = 1;
    #1 E = 1; J = 0; K = 1;
    #1 E = 1; J = 0; K = 1;
    #1 E = 1; J = 1; K = 0;
    #1 E = 1; J = 1; K = 0;
    #1 E = 1; J = 1; K = 0;
    #1 E = 1; J = 1; K = 0;
    #1 E = 1; J = 0; K = 0;
    #1 E = 1; J = 0; K = 0;
    #1 E = 1; J = 0; K = 0;
    #1 E = 1; J = 0; K = 0;
    #1 E = 1; J = 1; K = 1;
    #1 E = 1; J = 1; K = 1;
    #1 E = 1; J = 1; K = 1;
    #1 E = 1; J = 1; K = 1;

  end

  initial
    #30 $finish;

  initial begin
    $dumpfile("jkff_tb.vcd");
    $dumpvars(0, testbench);
  end

endmodule

E3/jkff_tb.vcd
$date
	Fri Oct 30 23:27:18 2020
$end
$version
	Icarus Verilog
$end
$timescale
	1ps
$end
$scope module testbench $end
$var wire 1 ! w2 $end
$var wire 1 " w1 $end
$var wire 1 # nQp $end
$var wire 1 $ nK $end
$var wire 1 % Qp $end
$var wire 1 & Qn $end
$var reg 1 ' E $end
$var reg 1 ( J $end
$var reg 1 ) K $end
$var reg 1 * clk $end
$var reg 1 + reset $end
$scope module jkf1 $end
$var wire 1 ' E $end
$var wire 1 ( J $end
$var wire 1 ) K $end
$var wire 1 & Qn $end
$var wire 1 * clk2 $end
$var wire 1 $ nK $end
$var wire 1 # nQp $end
$var wire 1 , reset $end
$var wire 1 + reset2 $end
$var wire 1 " w1 $end
$var wire 1 ! w2 $end
$var wire 1 % Qp $end
$scope module D1 $end
$var wire 1 & D $end
$var wire 1 ' E $end
$var wire 1 * clk $end
$var wire 1 , reset $end
$var reg 1 % Q $end
$upscope $end
$upscope $end
$upscope $end
$enddefinitions $end
#0
$dumpvars
z,
1+
0*
x)
x(
x'
x&
x%
x$
x#
x"
x!
$end
#1
1$
0!
0)
0(
0'
0+
1*
#2
0&
0"
0$
1)
1'
0*
#3
1#
0%
1*
#4
0*
#5
1*
#6
1&
1$
1!
0)
1(
0*
#7
0!
1"
0#
1%
1*
#8
0*
#9
1*
#10
0(
0*
#11
1*
#12
0*
#13
1*
#14
0&
0"
0$
1)
1(
0*
#15
1&
1!
1#
0%
1*
#16
0*
#17
0&
0!
0#
1%
1*
#18
0*
#19
1&
1!
1#
0%
1*
#20
0*
#21
0&
0!
0#
1%
1*
#22
0*
#23
1&
1!
1#
0%
1*
#24
0*
#25
0&
0!
0#
1%
1*
#26
0*
#27
1&
1!
1#
0%
1*
#28
0*
#29
0&
0!
0#
1%
1*
