E2/tff.v
//Univseridad del Valle de Guatemala
//Gerardo Fuentes
//19389


//Modulo Flipflop tipo D 1 BIT
module DFF1b(input clk, reset, E, D, output reg Q);

  always@(posedge clk, posedge reset, E)
    if (reset)  Q<=1'b0;
    else if (E) Q<=D;

endmodule


//Modulo Flipflop tipo T 1 BIT
module TFF1b(input clk, reset, E, output Q, QA);

  not (QA,Q);
  DFF1b D1(clk, reset, E, QA, Q);

endmodule

E2/tff_tb.v
//Univseridad del Valle de Guatemala
//Gerardo Fuentes
//19389

module testbench();

  reg clk, reset, E;
  wire Q1, Q1A;


  TFF1b tf1(clk, reset, E, Q1, Q1A);


  initial begin
     clk = 0;
     forever #1 clk = ~clk;
  end

  initial begin
    reset = 1;
    #1 reset = 0;
  end

  initial begin
    #1 E = 0;
    #1 E = 1;
    #1 E = 1;
    #1 E = 1;
    #1 E = 1;
    #1 E = 1;
    #1 E = 1;
    #1 E = 1;
    #1 E = 1;
    #1 E = 1;
    #1 E = 1;
    #1 E = 1;
    #1 E = 1;
    #1 E = 1;
    #1 E = 1;
    #1 E = 1;
    #1 E = 1;
    #1 E = 1;
    #1 E = 1;
    #1 E = 1;
    #1 E = 1;
    #1 E = 1;
    #1 E = 0;
    #1 E = 0;
    #1 E = 0;
    #1 E = 0;
    #1 E = 0;
  end

  initial
    #30 $finish;

  initial begin
    $dumpfile("tff_tb.vcd");
    $dumpvars(0, testbench);
  end

endmodule

E2/tff_tb.vcd
$date
	Fri Oct 30 23:10:17 2020
$end
$version
	Icarus Verilog
$end
$timescale
	1ps
$end
$scope module testbench $end
$var wire 1 ! Q1A $end
$var wire 1 " Q1 $end
$var reg 1 # E $end
$var reg 1 $ clk $end
$var reg 1 % reset $end
$scope module tf1 $end
$var wire 1 # E $end
$var wire 1 ! QA $end
$var wire 1 $ clk $end
$var wire 1 % reset $end
$var wire 1 " Q $end
$scope module D1 $end
$var wire 1 ! D $end
$var wire 1 # E $end
$var wire 1 $ clk $end
$var wire 1 % reset $end
$var reg 1 " Q $end
$upscope $end
$upscope $end
$upscope $end
$enddefinitions $end
#0
$dumpvars
1%
0$
x#
0"
1!
$end
#1
0#
0%
1$
#2
0!
1"
1#
0$
#3
1!
0"
1$
#4
0$
#5
0!
1"
1$
#6
0$
#7
1!
0"
1$
#8
0$
#9
0!
1"
1$
#10
0$
#11
1!
0"
1$
#12
0$
#13
0!
1"
1$
#14
0$
#15
1!
0"
1$
#16
0$
#17
0!
1"
1$
#18
0$
#19
1!
0"
1$
#20
0$
#21
0!
1"
1$
#22
0$
#23
0#
1$
