E4/buff.v
//Univseridad del Valle de Guatemala
//Gerardo Fuentes
//19389


//Modulo Buffer triestado 4 bits
module buff4b(input E, input[3:0]D, output [3:0]Q);

  assign Q = E == 1 ? D:4'bz;

endmodule

E4/buff_tb.v
//Univseridad del Valle de Guatemala
//Gerardo Fuentes
//19389

module testbench();

  reg E;
  reg[3:0]D;
  wire[3:0]Q;

  buff4b b4(E, D, Q);

  initial begin
    #1 E = 1; D = 4'b0000;
    #1 E = 1; D = 4'b0000;
    #1 E = 1; D = 4'b0000;
    #1 E = 1; D = 4'b0000;
    #1 E = 1; D = 4'b1000;
    #1 E = 1; D = 4'b1000;
    #1 E = 1; D = 4'b1000;
    #1 E = 1; D = 4'b1001;
    #1 E = 1; D = 4'b1001;
    #1 E = 1; D = 4'b1001;
    #1 E = 1; D = 4'b1111;
    #1 E = 1; D = 4'b1111;
    #1 E = 1; D = 4'b1111;
    #1 E = 1; D = 4'b1010;
    #1 E = 1; D = 4'b1010;
    #1 E = 1; D = 4'b1010;
    #1 E = 1; D = 4'b1100;
    #1 E = 1; D = 4'b1100;
    #1 E = 1; D = 4'b1100;
    #1 E = 1; D = 4'b1000;
    #1 E = 1; D = 4'b1000;
    #1 E = 0; D = 4'b1000;
    #1 E = 0; D = 4'b1100;
    #1 E = 0; D = 4'b1110;
    #1 E = 0; D = 4'b1111;
    #1 E = 0; D = 4'b1010;
  end

  initial
    #30 $finish;

  initial begin
    $dumpfile("buff_tb.vcd");
    $dumpvars(0, testbench);
  end

  endmodule

E4/buff_tb.vcd
$date
	Sat Oct 31 02:48:12 2020
$end
$version
	Icarus Verilog
$end
$timescale
	1ps
$end
$scope module testbench $end
$var wire 4 ! Q [3:0] $end
$var reg 4 " D [3:0] $end
$var reg 1 # E $end
$scope module b4 $end
$var wire 4 $ D [3:0] $end
$var wire 1 # E $end
$var wire 4 % Q [3:0] $end
$upscope $end
$upscope $end
$enddefinitions $end
#0
$dumpvars
bx %
bx $
x#
bx "
bx !
$end
#1
b0 !
b0 %
b0 "
b0 $
1#
#5
b1000 !
b1000 %
b1000 "
b1000 $
#8
b1001 !
b1001 %
b1001 "
b1001 $
#11
b1111 !
b1111 %
b1111 "
b1111 $
#14
b1010 !
b1010 %
b1010 "
b1010 $
#17
b1100 !
b1100 %
b1100 "
b1100 $
#20
b1000 !
b1000 %
b1000 "
b1000 $
#22
bz !
bz %
0#
#23
b1100 "
b1100 $
#24
b1110 "
b1110 $
#25
b1111 "
b1111 $
#26
b1010 "
b1010 $
