E1/dff.v
//Univseridad del Valle de Guatemala
//Gerardo Fuentes
//19389


//Modulo Flipflop tipo D 1 BIT
module DFF1b(input clk, reset, E, D, output reg Q);

  always@(posedge clk, posedge reset, E)
    if (reset)  Q<=1'b0;
    else if (E) Q<=D;

endmodule


//Modulo Flipflop tipo D 2 BIT
module DFF2b(input clk2, reset2, E2, input[1:0] D2, output[1:0] Q2);

  DFF1b df1(clk2, reset2, E2, D2[1], Q2[1]);
  DFF1b df0(clk2, reset2, E2, D2[0], Q2[0]);

endmodule

//Modulo Flipflop tipo D 4 BIT
module DFF4b(input clk4, reset4, E4, input[3:0] D4, output[3:0] Q4);

  DFF2b df32(clk4, reset4, E4, D4[3:2], Q4[3:2]);
  DFF2b df10(clk4, reset4, E4, D4[1:0], Q4[1:0]);

endmodule

E1/dff_tb.v
//Univseridad del Valle de Guatemala
//Gerardo Fuentes
//19389

module testbench();

  reg clk, reset, D1, E;
  reg[1:0] D2;
  reg[3:0] D4;
  wire Q1;
  wire[1:0] Q2;
  wire[3:0] Q4;

  DFF1b Df1(clk, reset, E, D1, Q1);
  DFF2b Df2(clk, reset, E, D2, Q2);
  DFF4b Df4(clk, reset, E, D4, Q4);

  initial begin
     clk = 0;
     forever #1 clk = ~clk;
  end

  initial begin
    reset = 1;
    #1 reset = 0;
  end

  initial begin
    #1 E = 0; D1 = 0; D2 = 2'b00; D4 = 4'b0000;
    #1 E = 1; D1 = 1; D2 = 2'b01; D4 = 4'b0001;
    #1 E = 1; D1 = 1; D2 = 2'b01; D4 = 4'b0001;
    #1 E = 1; D1 = 0; D2 = 2'b00; D4 = 4'b0000;
    #1 E = 1; D1 = 0; D2 = 2'b00; D4 = 4'b0000;
    #1 E = 1; D1 = 1; D2 = 2'b01; D4 = 4'b0001;
    #1 E = 1; D1 = 1; D2 = 2'b01; D4 = 4'b0001;
    #1 E = 0; D1 = 0; D2 = 2'b00; D4 = 4'b0000;
    #1 E = 0; D1 = 0; D2 = 2'b00; D4 = 4'b0000;
    #1 E = 0; D1 = 1; D2 = 2'b01; D4 = 4'b0001;
    #1 E = 0; D1 = 1; D2 = 2'b01; D4 = 4'b0001;
    #1 E = 0; D1 = 0; D2 = 2'b01; D4 = 4'b0001;
    #1 E = 0; D1 = 0; D2 = 2'b01; D4 = 4'b0001;

  end

  initial
    #10 $finish;

  initial begin
    $dumpfile("dff_tb.vcd");
    $dumpvars(0, testbench);
  end

endmodule

E1/dff_tb.vcd
$date
	Sat Oct 31 02:41:34 2020
$end
$version
	Icarus Verilog
$end
$timescale
	1ps
$end
$scope module testbench $end
$var wire 4 ! Q4 [3:0] $end
$var wire 2 " Q2 [1:0] $end
$var wire 1 # Q1 $end
$var reg 1 $ D1 $end
$var reg 2 % D2 [1:0] $end
$var reg 4 & D4 [3:0] $end
$var reg 1 ' E $end
$var reg 1 ( clk $end
$var reg 1 ) reset $end
$scope module Df1 $end
$var wire 1 $ D $end
$var wire 1 ' E $end
$var wire 1 ( clk $end
$var wire 1 ) reset $end
$var reg 1 # Q $end
$upscope $end
$scope module Df2 $end
$var wire 2 * D2 [1:0] $end
$var wire 1 ' E2 $end
$var wire 1 ( clk2 $end
$var wire 1 ) reset2 $end
$var wire 2 + Q2 [1:0] $end
$scope module df0 $end
$var wire 1 , D $end
$var wire 1 ' E $end
$var wire 1 ( clk $end
$var wire 1 ) reset $end
$var reg 1 - Q $end
$upscope $end
$scope module df1 $end
$var wire 1 . D $end
$var wire 1 ' E $end
$var wire 1 ( clk $end
$var wire 1 ) reset $end
$var reg 1 / Q $end
$upscope $end
$upscope $end
$scope module Df4 $end
$var wire 4 0 D4 [3:0] $end
$var wire 1 ' E4 $end
$var wire 1 ( clk4 $end
$var wire 1 ) reset4 $end
$var wire 4 1 Q4 [3:0] $end
$scope module df10 $end
$var wire 2 2 D2 [1:0] $end
$var wire 1 ' E2 $end
$var wire 1 ( clk2 $end
$var wire 1 ) reset2 $end
$var wire 2 3 Q2 [1:0] $end
$scope module df0 $end
$var wire 1 4 D $end
$var wire 1 ' E $end
$var wire 1 ( clk $end
$var wire 1 ) reset $end
$var reg 1 5 Q $end
$upscope $end
$scope module df1 $end
$var wire 1 6 D $end
$var wire 1 ' E $end
$var wire 1 ( clk $end
$var wire 1 ) reset $end
$var reg 1 7 Q $end
$upscope $end
$upscope $end
$scope module df32 $end
$var wire 2 8 D2 [1:0] $end
$var wire 1 ' E2 $end
$var wire 1 ( clk2 $end
$var wire 1 ) reset2 $end
$var wire 2 9 Q2 [1:0] $end
$scope module df0 $end
$var wire 1 : D $end
$var wire 1 ' E $end
$var wire 1 ( clk $end
$var wire 1 ) reset $end
$var reg 1 ; Q $end
$upscope $end
$scope module df1 $end
$var wire 1 < D $end
$var wire 1 ' E $end
$var wire 1 ( clk $end
$var wire 1 ) reset $end
$var reg 1 = Q $end
$upscope $end
$upscope $end
$upscope $end
$upscope $end
$enddefinitions $end
#0
$dumpvars
0=
x<
0;
x:
b0 9
bx 8
07
x6
05
x4
b0 3
bx 2
b0 1
bx 0
0/
x.
0-
x,
b0 +
bx *
1)
0(
x'
bx &
bx %
x$
0#
b0 "
b0 !
$end
#1
0<
0:
06
04
b0 8
b0 2
0.
0,
b0 &
b0 0
b0 %
b0 *
0$
0'
0)
1(
#2
1#
14
b1 2
1,
b1 &
b1 0
b1 %
b1 *
1$
1'
0(
#3
b1 !
b1 1
b1 3
15
b1 "
b1 +
1-
1(
#4
04
b0 2
0,
b0 &
b0 0
b0 %
b0 *
0$
0(
#5
0#
b0 "
b0 +
0-
b0 !
b0 1
b0 3
05
1(
#6
14
b1 2
1,
b1 &
b1 0
b1 %
b1 *
1$
0(
#7
b1 !
b1 1
b1 3
15
b1 "
b1 +
1-
1#
1(
#8
04
b0 2
0,
b0 &
b0 0
b0 %
b0 *
0$
0'
0(
#9
1(
#10
14
b1 2
1,
b1 &
b1 0
b1 %
b1 *
1$
0(
